analyze_id_package/__init__.py
analyze_id_package/id_analyzer.py
analyze_id_package-0.1.dist-info/METADATA
analyze_id_package-0.1.dist-info/WHEEL
analyze_id_package-0.1.dist-info/top_level.txt
analyze_id_package-0.1.dist-info/RECORD
