Metadata-Version: 2.1
Name: analyze-id-package
Version: 0.1
Summary: A Python package to analyze identity documents using AWS Textract's AnalyzeID feature.
Author: Swarup Adhikary
Author-email: swarup.ogma@example.com
License: MIT
Classifier: Programming Language :: Python :: 3
Classifier: License :: OSI Approved :: MIT License
Classifier: Operating System :: OS Independent
Requires-Python: >=3.6
Requires-Dist: boto3
